LoggerBek/LoggerBek.py
LoggerBek/__init__.py
LoggerBek-0.0.4.dist-info/LICENSE
LoggerBek-0.0.4.dist-info/METADATA
LoggerBek-0.0.4.dist-info/WHEEL
LoggerBek-0.0.4.dist-info/top_level.txt
LoggerBek-0.0.4.dist-info/RECORD
